jettask/__init__.py
jettask/cli.py
jettask/exceptions.py
jettask/config/__init__.py
jettask/config/constants.py
jettask/config/env_loader.py
jettask/config/lua_scripts.py
jettask/config/nacos_config.py
jettask/config/task_center.py
jettask/core/__init__.py
jettask/core/app.py
jettask/core/app_importer.py
jettask/core/center_client.py
jettask/core/context.py
jettask/core/enums.py
jettask/core/message.py
jettask/core/namespace.py
jettask/core/namespace_manager_base.py
jettask/core/retry.py
jettask/core/task.py
jettask/db/__init__.py
jettask/db/base.py
jettask/db/connector.py
jettask/db/models/__init__.py
jettask/db/models/asset.py
jettask/db/models/namespace.py
jettask/db/models/scheduled_task.py
jettask/db/models/sql_history.py
jettask/db/models/task.py
jettask/db/models/task_metrics_minute.py
jettask/db/models/task_run.py
jettask/db/models/task_runs_metrics_minute.py
jettask/db/models/webhook.py
jettask/executor/__init__.py
jettask/executor/core.py
jettask/executor/orchestrator.py
jettask/executor/process_entry.py
jettask/executor/task_executor.py
jettask/messaging/__init__.py
jettask/messaging/delay_queue.py
jettask/messaging/event_pool.py
jettask/messaging/reader.py
jettask/messaging/registry.py
jettask/messaging/sender.py
jettask/persistence/__init__.py
jettask/persistence/buffer.py
jettask/persistence/consumer.py
jettask/persistence/manager.py
jettask/persistence/persistence.py
jettask/scheduler/__init__.py
jettask/scheduler/definition.py
jettask/scheduler/manager.py
jettask/scheduler/scheduler.py
jettask/scheduler/sql/002_rename_scheduled_until_to_next_trigger_time.sql
jettask/schemas/__init__.py
jettask/schemas/alert.py
jettask/schemas/asset.py
jettask/schemas/auth.py
jettask/schemas/backlog.py
jettask/schemas/common.py
jettask/schemas/monitoring.py
jettask/schemas/namespace.py
jettask/schemas/queue.py
jettask/schemas/responses.py
jettask/schemas/scheduled_task.py
jettask/schemas/schema.sql
jettask/schemas/task.py
jettask/schemas/webhook.py
jettask-1.0.59.dist-info/licenses/LICENSE
jettask-1.0.59.dist-info/METADATA
jettask-1.0.59.dist-info/WHEEL
jettask-1.0.59.dist-info/entry_points.txt
jettask-1.0.59.dist-info/top_level.txt
jettask-1.0.59.dist-info/RECORD
