Metadata-Version: 2.4
Name: jettask
Version: 1.0.59
Summary: A high-performance distributed task queue system with web monitoring
Author-email: JetTask Team <support@jettask.io>
License-Expression: MIT
Project-URL: Homepage, https://github.com/yourusername/jettask
Project-URL: Bug Tracker, https://github.com/yourusername/jettask/issues
Project-URL: Documentation, https://jettask.readthedocs.io
Classifier: Development Status :: 4 - Beta
Classifier: Intended Audience :: Developers
Classifier: Topic :: Software Development :: Libraries :: Python Modules
Classifier: Topic :: System :: Distributed Computing
Classifier: Programming Language :: Python :: 3
Classifier: Programming Language :: Python :: 3.8
Classifier: Programming Language :: Python :: 3.9
Classifier: Programming Language :: Python :: 3.10
Classifier: Programming Language :: Python :: 3.11
Classifier: Operating System :: OS Independent
Requires-Python: >=3.8
License-File: LICENSE
Requires-Dist: redis
Requires-Dist: msgpack>=1.0.0
Requires-Dist: pydantic>=2.0.0
Requires-Dist: click>=8.1.0
Requires-Dist: croniter>=1.4.0
Requires-Dist: aiohttp>=3.8.0
Requires-Dist: uvloop>=0.17.0; sys_platform == "linux"
Provides-Extra: webui
Requires-Dist: fastapi>=0.100.0; extra == "webui"
Requires-Dist: uvicorn[standard]>=0.23.0; extra == "webui"
Requires-Dist: python-multipart>=0.0.6; extra == "webui"
Requires-Dist: ujson>=5.6.0; extra == "webui"
Requires-Dist: sqlalchemy[asyncio]>=2.0.0; extra == "webui"
Requires-Dist: asyncpg>=0.28.0; extra == "webui"
Requires-Dist: nacos-sdk-python==2.0.9; extra == "webui"
Requires-Dist: PyJWT>=2.8.0; extra == "webui"
Provides-Extra: extra
Requires-Dist: python-dotenv>=1.0.0; extra == "extra"
Requires-Dist: psutil>=5.9.0; extra == "extra"
Provides-Extra: all
Requires-Dist: jettask[extra,webui]; extra == "all"
Provides-Extra: dev
Requires-Dist: black>=23.0; extra == "dev"
Requires-Dist: flake8>=6.0; extra == "dev"
Requires-Dist: mypy>=1.4.0; extra == "dev"
Requires-Dist: coverage>=7.0; extra == "dev"
Dynamic: license-file
